uploadtodalas/__init__.py
uploadtodalas/upload.py
uploadtodalas-1.0.0.dist-info/LICENSE
uploadtodalas-1.0.0.dist-info/METADATA
uploadtodalas-1.0.0.dist-info/WHEEL
uploadtodalas-1.0.0.dist-info/top_level.txt
uploadtodalas-1.0.0.dist-info/RECORD
