Metadata-Version: 2.1
Name: uploadtodalas
Version: 1.0.0
Summary: Пакет для загрузки файлов в сервис Dalas, включает как методы для обычных пользователей, так и методы для панелей
Home-page: https://api.uploadgroup.site/docs
Author: Dalas
Author-email: email@uploadgroup.site
Classifier: Programming Language :: Python :: 3
Classifier: License :: OSI Approved :: MIT License
Classifier: Operating System :: OS Independent
Requires-Python: >=3.5
License-File: LICENSE
Requires-Dist: aiohttp >=3.7.4
Requires-Dist: loguru >=0.5.3
